email_deliverability/__init__.py
email_deliverability/cli.py
email_deliverability/facade.py
email_deliverability/resource_manager.py
email_deliverability/utils.py
email_deliverability/authentication/__init__.py
email_deliverability/authentication/dkim.py
email_deliverability/authentication/dmarc.py
email_deliverability/authentication/spf.py
email_deliverability/authentication/utils.py
email_deliverability/ip_warming/__init__.py
email_deliverability/ip_warming/monitor.py
email_deliverability/ip_warming/scheduler.py
email_deliverability/list_hygiene/__init__.py
email_deliverability/list_hygiene/bounce_handler.py
email_deliverability/list_hygiene/cleaner.py
email_deliverability/list_hygiene/validator.py
email_deliverability/reputation/__init__.py
email_deliverability/reputation/analyze.py
email_deliverability/reputation/monitor.py
email_deliverability-0.1.3.dist-info/licenses/LICENSE
email_deliverability-0.1.3.dist-info/METADATA
email_deliverability-0.1.3.dist-info/WHEEL
email_deliverability-0.1.3.dist-info/entry_points.txt
email_deliverability-0.1.3.dist-info/top_level.txt
email_deliverability-0.1.3.dist-info/RECORD
