Metadata-Version: 2.4
Name: email_deliverability
Version: 0.1.3
Summary: Comprehensive email deliverability management tools
Home-page: https://github.com/innerkore/email-deliverability
Author: Gagan (InnerKore)
Author-email: gagan@innerkore.com
Project-URL: Documentation, https://github.com/innerkore/email-deliverability/docs
Project-URL: Source, https://github.com/innerkore/email-deliverability
Project-URL: Tracker, https://github.com/innerkore/email-deliverability/issues
Keywords: email,deliverability,spf,dkim,dmarc,email authentication
Classifier: Development Status :: 4 - Beta
Classifier: Intended Audience :: Developers
Classifier: License :: OSI Approved :: MIT License
Classifier: Programming Language :: Python :: 3
Classifier: Programming Language :: Python :: 3.7
Classifier: Programming Language :: Python :: 3.8
Classifier: Programming Language :: Python :: 3.9
Classifier: Programming Language :: Python :: 3.10
Classifier: Programming Language :: Python :: 3.11
Classifier: Programming Language :: Python :: 3.12
Classifier: Topic :: Communications :: Email
Requires-Python: >=3.7
License-File: LICENSE
Requires-Dist: dnspython>=2.0.0
Requires-Dist: requests>=2.25.0
Requires-Dist: cryptography>=3.2.0
Requires-Dist: schedule>=1.2.0
Provides-Extra: dev
Requires-Dist: pytest; extra == "dev"
Requires-Dist: pytest-cov; extra == "dev"
Requires-Dist: sphinx; extra == "dev"
Requires-Dist: sphinx_rtd_theme; extra == "dev"
Requires-Dist: twine==6.0.1; extra == "dev"
Requires-Dist: black>=20.8b1; extra == "dev"
Requires-Dist: isort>=5.7.0; extra == "dev"
Requires-Dist: flake8>=3.8.0; extra == "dev"
Requires-Dist: myst-parser>=0.18.0; extra == "dev"
Requires-Dist: wheel; extra == "dev"
Requires-Dist: build; extra == "dev"
Provides-Extra: docs
Requires-Dist: sphinx; extra == "docs"
Requires-Dist: sphinx_rtd_theme; extra == "docs"
Dynamic: author
Dynamic: author-email
Dynamic: classifier
Dynamic: description
Dynamic: description-content-type
Dynamic: home-page
Dynamic: keywords
Dynamic: license-file
Dynamic: project-url
Dynamic: provides-extra
Dynamic: requires-dist
Dynamic: requires-python
Dynamic: summary
